[
  {
    "author": "Neceros",
    "name": "SRTS Expanded Realism Patch",
    "steamId": null,
    "version": null
  },
  {
    "author": "Nitrodev",
    "name": "Absolutely No Roof",
    "steamId": null,
    "version": null
  },
  {
    "author": "Kentington and Thain",
    "name": "Save Our Ship 2",
    "steamId": null,
    "version": null
  },
  {
    "author": "Inglix",
    "name": "Apparel Tainted Only When Corpse Rots",
    "steamId": null,
    "version": null
  },
  {
    "author": "Razor 2.3",
    "name": "Auto-Cut Blight",
    "steamId": null,
    "version": null
  },
  {
    "author": "UnlimitedHugs",
    "name": "Allow Tool",
    "steamId": null,
    "version": null
  },
  {
    "author": "FluffyKittens",
    "name": "Categorized Bill Dropdown",
    "steamId": null,
    "version": null
  },
  {
    "author": "Kapitan Oczywisty",
    "name": "Change map edge limit",
    "steamId": null,
    "version": null
  },
  {
    "author": "Oskar Potocki and  Kikohi",
    "name": "Vanilla Expanded - Ideology Patches",
    "steamId": null,
    "version": null
  },
  {
    "author": "Oskar Potocki and  Kikohi",
    "name": "Vanilla Expanded - Royalty Patches",
    "steamId": null,
    "version": null
  },
  {
    "author": "Anon",
    "name": "Clean Vanilla Expanded",
    "steamId": null,
    "version": null
  },
  {
    "author": "8Z",
    "name": "Cook Carefully",
    "steamId": null,
    "version": null
  },
  {
    "author": "UnlimitedHugs",
    "name": "Defensive Positions",
    "steamId": null,
    "version": null
  },
  {
    "author": "tikubonn",
    "name": "DontBlockDoor",
    "steamId": null,
    "version": null
  },
  {
    "author": "DarkFlame7",
    "name": "Factorio Music",
    "steamId": null,
    "version": null
  },
  {
    "author": "Aelanna",
    "name": "Fists Aren't Made of Steel",
    "steamId": null,
    "version": null
  },
  {
    "author": "Dyrewulfe",
    "name": "Food Poisoning Stack Fix (Continued)",
    "steamId": null,
    "version": null
  },
  {
    "author": "ItsComcastic",
    "name": "Haul to Stack",
    "steamId": null,
    "version": null
  },
  {
    "author": "OkraDonkey",
    "name": "Infinite Torches",
    "steamId": null,
    "version": null
  },
  {
    "author": "Andreas Pardeike",
    "name": "Just Ignore Me Passing",
    "steamId": null,
    "version": null
  },
  {
    "author": "dhultgren",
    "name": "Keep Bed Ownership",
    "steamId": null,
    "version": null
  },
  {
    "author": "UnlimitedHugs",
    "name": "Map Reroll",
    "steamId": null,
    "version": null
  },
  {
    "author": "Canguro",
    "name": "Mechanoid better loot",
    "steamId": null,
    "version": null
  },
  {
    "author": "Haplo",
    "name": "Misc. Robots",
    "steamId": null,
    "version": null
  },
  {
    "author": "Antaios",
    "name": "Mod Medicine Patch",
    "steamId": null,
    "version": null
  },
  {
    "author": "SineSwiper",
    "name": "More Drug Stats",
    "steamId": null,
    "version": null
  },
  {
    "author": "Oskar Potocki and  Taranchuk",
    "name": "Vanilla Books Expanded",
    "steamId": null,
    "version": null
  },
  {
    "author": "purpleyam",
    "name": "More Ideological Words",
    "steamId": null,
    "version": null
  },
  {
    "author": "Xell",
    "name": "More Trade Ships",
    "steamId": null,
    "version": null
  },
  {
    "author": "Bishop",
    "name": "Music on the Rim",
    "steamId": null,
    "version": null
  },
  {
    "author": "Unon",
    "name": "No Burn Metal",
    "steamId": null,
    "version": null
  },
  {
    "author": "OkraDonkey",
    "name": "No Edge Fade - Lite",
    "steamId": null,
    "version": null
  },
  {
    "author": "Zaljerem",
    "name": "Orbital Animal Traders (Continued)",
    "steamId": null,
    "version": null
  },
  {
    "author": "XelNigma",
    "name": "Psy-Eltex",
    "steamId": null,
    "version": null
  },
  {
    "author": "SGC",
    "name": "Quest Reward Rebalance",
    "steamId": null,
    "version": null
  },
  {
    "author": "VibeCheque",
    "name": "Realistic Rooms 1.3",
    "steamId": null,
    "version": null
  },
  {
    "author": "SirMcKeon",
    "name": "Reasonable Components",
    "steamId": null,
    "version": null
  },
  {
    "author": "Jaxe",
    "name": "RimHUD",
    "steamId": null,
    "version": null
  },
  {
    "author": "Dakk Passerida",
    "name": "Replantable Anima Trees",
    "steamId": null,
    "version": null
  },
  {
    "author": "Rizno",
    "name": "RimFTL (Music Pack)",
    "steamId": null,
    "version": null
  },
  {
    "author": "Orion",
    "name": "Hospitality",
    "steamId": null,
    "version": null
  },
  {
    "author": "Mlie",
    "name": "Run and Hide (Continued)",
    "steamId": null,
    "version": null
  },
  {
    "author": "Roolo and Updated by Ogliss",
    "name": "RunAndGun",
    "steamId": null,
    "version": null
  },
  {
    "author": "Roolo",
    "name": "Search and Destroy",
    "steamId": null,
    "version": null
  },
  {
    "author": "dhultgren",
    "name": "Smarter Construction",
    "steamId": null,
    "version": null
  },
  {
    "author": "LM",
    "name": "Smokeleaf Tweaks",
    "steamId": null,
    "version": null
  },
  {
    "author": "Evelyn",
    "name": "Consistent Map Stone",
    "steamId": null,
    "version": null
  },
  {
    "author": "zhrock11",
    "name": "Stackable Chunks [1.3+]",
    "steamId": null,
    "version": null
  },
  {
    "author": "Abby Sciuto",
    "name": "Sun Lamp Power",
    "steamId": null,
    "version": null
  },
  {
    "author": "Sam",
    "name": "Tilled Soil",
    "steamId": null,
    "version": null
  },
  {
    "author": "Smash Phil",
    "name": "Trade Ships Drop Spot",
    "steamId": null,
    "version": null
  },
  {
    "author": "Hob Took",
    "name": "Trade UI Revised",
    "steamId": null,
    "version": null
  },
  {
    "author": "Kikohi and Oskar Potocki",
    "name": "Vanilla Base Generation Expanded",
    "steamId": null,
    "version": null
  },
  {
    "author": "Toasteh and  Updated by Ogliss",
    "name": "Veinminer R1.1",
    "steamId": null,
    "version": null
  },
  {
    "author": "Kathanon",
    "name": "Weather Duration",
    "steamId": null,
    "version": null
  },
  {
    "author": "Derek Bickley",
    "name": "Worthless Junk",
    "steamId": null,
    "version": null
  },
  {
    "author": "CopperMonster",
    "name": "[CM] Spots Tab",
    "steamId": null,
    "version": null
  },
  {
    "author": "FrozenSnowFox",
    "name": "[FSF] Better Ancient Complex Loot",
    "steamId": null,
    "version": null
  },
  {
    "author": "FrozenSnowFox",
    "name": "[FSF] Better Camp Loot",
    "steamId": null,
    "version": null
  },
  {
    "author": "FrozenSnowFox",
    "name": "[FSF] Filth Vanishes With Rain And Time",
    "steamId": null,
    "version": null
  },
  {
    "author": "FrozenSnowFox",
    "name": "[FSF] Growable Grass",
    "steamId": null,
    "version": null
  },
  {
    "author": "Neronix17",
    "name": "[O21] Ancient Demolition",
    "steamId": null,
    "version": null
  },
  {
    "author": "Chicken Plucker and  Taranchuk",
    "name": "[RH2] BCD: First Aid",
    "steamId": null,
    "version": null
  }
]